{
    "name": "连锁爆分3",
    "saveData": {
        "version": 104,
        "team": [
            {
                "hp": 6,
                "smile": 4330,
                "pure": 4240,
                "cool": 6350,
                "skilllevel": 8,
                "gemlist": [
                    "SCORE_250",
                    "MEMBER_29"
                ],
                "cardid": 2051,
                "mezame": 1,
                "maxcost": 8
            },
            {
                "hp": 4,
                "smile": 3650,
                "pure": 5260,
                "cool": 3820,
                "skilllevel": 8,
                "gemlist": [
                    "SCORE_250"
                ],
                "cardid": 162,
                "mezame": 1,
                "maxcost": 4
            },
            {
                "hp": 4,
                "smile": 3650,
                "pure": 5260,
                "cool": 3820,
                "skilllevel": 8,
                "gemlist": [
                    "SCORE_250"
                ],
                "cardid": 162,
                "mezame": 1,
                "maxcost": 4
            },
            {
                "hp": 6,
                "smile": 6350,
                "pure": 4500,
                "cool": 4100,
                "skilllevel": 8,
                "gemlist": [
                    "AMUL_24",
                    "MEMBER_29"
                ],
                "cardid": 1415,
                "mezame": 1,
                "maxcost": 8
            },
            {
                "hp": 6,
                "smile": 6280,
                "pure": 4160,
                "cool": 4380,
                "skilllevel": 8,
                "gemlist": [
                    "AMUL_24",
                    "MEMBER_29"
                ],
                "cardid": 1479,
                "mezame": 1,
                "maxcost": 8
            },
            {
                "hp": 4,
                "smile": 3800,
                "pure": 3690,
                "cool": 5140,
                "skilllevel": 8,
                "gemlist": [
                    "SCORE_250"
                ],
                "cardid": 182,
                "mezame": 1,
                "maxcost": 4
            },
            {
                "hp": 4,
                "smile": 3800,
                "pure": 3690,
                "cool": 5140,
                "skilllevel": 8,
                "gemlist": [
                    "SCORE_250"
                ],
                "cardid": 182,
                "mezame": 1,
                "maxcost": 4
            },
            {
                "hp": 4,
                "smile": 3800,
                "pure": 3690,
                "cool": 5140,
                "skilllevel": 8,
                "gemlist": [
                    "SCORE_250"
                ],
                "cardid": 182,
                "mezame": 1,
                "maxcost": 4
            },
            {
                "hp": 6,
                "smile": 4330,
                "pure": 4240,
                "cool": 6350,
                "skilllevel": 8,
                "gemlist": [
                    "SCORE_250",
                    "MEMBER_29"
                ],
                "cardid": 2051,
                "mezame": 1,
                "maxcost": 8
            }
        ],
        "gemstock": {},
        "submember": []
    },
    "songId": "225",
    "songSettingId": "775",
    "version": "latest",
    "page": "llnewunit",
    "type": "sim",
    "map": {
        "attribute": "pure",
        "songUnit": 4,
        "combo": 993,
        "star": 75,
        "time": 111,
        "perfect": 844,
        "starPerfect": 75,
        "weights": [
            81.375,
            114,
            133.75,
            87,
            44.625,
            87.25,
            131.75,
            113,
            79.5
        ],
        "totalWeight": 872.25,
        "friendCSkill": {
            "attribute": "pure",
            "Cskillattribute": "pure",
            "Cskillpercentage": 0,
            "Csecondskilllimit": 1,
            "Csecondskillattribute": 0
        },
        "tapup": 0,
        "skillup": 0,
        "speed": 9,
        "combo_fever_pattern": 2,
        "over_heal_pattern": 1,
        "perfect_accuracy_pattern": 1,
        "trigger_limit_pattern": 1
    },
    "result": {
        "attrStrength": [
            5470,
            5260,
            5260,
            6738,
            6300,
            3690,
            3690,
            3690,
            5470
        ],
        "finalAttr": {
            "smile": 45678,
            "pure": 45568,
            "cool": 44240
        },
        "bonusAttr": {
            "smile": 5688,
            "pure": 0,
            "cool": 0
        },
        "totalStrength": 61501,
        "totalAttrStrength": 42602,
        "totalSkillStrength": 18899,
        "totalHP": 44,
        "averageSkillsActiveCount": [
            11.1465,
            12.99,
            12.98,
            10.0285,
            40.817,
            7.998,
            7.9975,
            7.9985,
            11.187
        ],
        "averageSkillsActiveChanceCount": [
            14.5025,
            47.995,
            47.8185,
            25.124,
            49,
            28.1365,
            28.207,
            28.4785,
            14.5025
        ],
        "averageSkillsActiveNoEffectCount": [
            0,
            0,
            0,
            0,
            0,
            0,
            0,
            0,
            0
        ],
        "averageSkillsActiveHalfEffectCount": [
            0,
            0,
            0,
            0,
            0,
            0,
            0,
            0,
            0
        ],
        "averageAccessoryActiveCount": [
            0,
            0,
            0,
            0,
            0,
            0,
            0,
            0,
            0
        ],
        "averageAccessoryActiveChanceCount": [
            0,
            0,
            0,
            0,
            0,
            0,
            0,
            0,
            0
        ],
        "averageAccessoryActiveNoEffectCount": [
            0,
            0,
            0,
            0,
            0,
            0,
            0,
            0,
            0
        ],
        "averageAccessoryActiveHalfEffectCount": [
            0,
            0,
            0,
            0,
            0,
            0,
            0,
            0,
            0
        ],
        "averageHeal": 0,
        "averageAccuracyNCoverage": 0,
        "naivePercentile": [
            991221,
            1020428,
            1025162,
            1028924,
            1032889,
            1036644,
            1039444,
            1041103,
            1043460,
            1044867,
            1046361,
            1048208,
            1049572,
            1051095,
            1052054,
            1052841,
            1053864,
            1054651,
            1055706,
            1056734,
            1057585,
            1058055,
            1058797,
            1059480,
            1060330,
            1061169,
            1061932,
            1062909,
            1063850,
            1064670,
            1065359,
            1066287,
            1067271,
            1068083,
            1068682,
            1069498,
            1070498,
            1071145,
            1071772,
            1072648,
            1073152,
            1073787,
            1074546,
            1075465,
            1076266,
            1076900,
            1077499,
            1077926,
            1078655,
            1079185,
            1079664,
            1080491,
            1081114,
            1081537,
            1082514,
            1083341,
            1084025,
            1084660,
            1085230,
            1085734,
            1086294,
            1086690,
            1087178,
            1087992,
            1088787,
            1089596,
            1090115,
            1091136,
            1091947,
            1092772,
            1093260,
            1093956,
            1094892,
            1095494,
            1096192,
            1096888,
            1097771,
            1098744,
            1099442,
            1100190,
            1101356,
            1102412,
            1103117,
            1104170,
            1105110,
            1106314,
            1107617,
            1108603,
            1109862,
            1110726,
            1112100,
            1113522,
            1114725,
            1115910,
            1117766,
            1119603,
            1122703,
            1125701,
            1129668,
            1136506,
            1169549
        ],
        "averageDamage": 0,
        "averageOverHealLevel": 0,
        "failRate": 0
    }
}